setup.py
thready.py
thready.egg-info/PKG-INFO
thready.egg-info/SOURCES.txt
thready.egg-info/dependency_links.txt
thready.egg-info/entry_points.txt
thready.egg-info/not-zip-safe
thready.egg-info/top_level.txt