Metadata-Version: 1.0
Name: thready
Version: 0.1.2
Summary: Simple wrapper for threaded execution.
Home-page: http://github.com/pudo/thready
Author: Friedrich Lindenberg
Author-email: friedrich@pudo.org
License: MIT
Keywords: threading
Platform: UNKNOWN
